bayes_splicing/__init__.py
bayes_splicing/independent_priors.py
bayes_splicing/loss_distribution.py
bayes_splicing/move.py
bayes_splicing/posterior_analysis.py
bayes_splicing/prior_distribution.py
bayes_splicing/smc.py
bayes_splicing/spliced_distribution.py
bayes_splicing/temperature.py
bayes_splicing-0.0.5.dist-info/LICENSE
bayes_splicing-0.0.5.dist-info/METADATA
bayes_splicing-0.0.5.dist-info/WHEEL
bayes_splicing-0.0.5.dist-info/top_level.txt
bayes_splicing-0.0.5.dist-info/RECORD
