Metadata-Version: 2.1
Name: bayes-splicing
Version: 0.0.5
Summary: Bayesian fit of splicing models with applications to insurance loss data
Home-page: https://github.com/LaGauffre/bayes-splicing
Author: Pierre-Olivier Goffard
Author-email: pierre.olivier.goffard@gmail.com
License: MIT
Platform: UNKNOWN
Classifier: License :: OSI Approved :: MIT License
Classifier: Programming Language :: Python :: 3
Classifier: Programming Language :: Python :: 3.7
Classifier: Intended Audience :: Science/Research
License-File: LICENSE
Requires-Dist: joblib
Requires-Dist: numba
Requires-Dist: numpy (>=1.17)
Requires-Dist: scipy (>=1.4)
Requires-Dist: matplotlib
Requires-Dist: pandas
Requires-Dist: seaborn
